mpwrapper/__init__.py
mpwrapper/fifo.py
mpwrapper/mpwrapper.py
mpwrapper/mpwrapper_tests.py
mpwrapper/progress_fn.py
mpwrapper-1.2.9.dist-info/METADATA
mpwrapper-1.2.9.dist-info/RECORD
mpwrapper-1.2.9.dist-info/WHEEL
mpwrapper-1.2.9.dist-info/top_level.txt
