Metadata-Version: 2.1
Name: mpwrapper
Version: 1.2.9
Summary: A simple wrapper written to make the use of Python multiprocessing easy to use
Home-page: https://github.com/lodder/python_mpwrapper
Author: Shaun Lodder
Author-email: shaun.lodder@gmail.com
License: UNKNOWN
Keywords: multiprocessing
Platform: UNKNOWN
Classifier: Programming Language :: Python
Provides-Extra: develop
Requires-Dist: setuptools
Requires-Dist: numpy
Provides-Extra: develop
Requires-Dist: nose; extra == 'develop'
